[
  {
    "版面": "06版：国际观察",
    "文章标题": "投资中国，就是投资未来（观象台）",
    "摘要": "多年来，中国经济取得了举世瞩目的成就。如今，中国已成为欧莱雅全球第二大市场，我们见证了中国从蓬勃发展的消费市场，跃升为全球价值创造的战略高地。这进一步坚定了我们一贯的信念——投资中国，就是投资未来。 这份信念，早在1997年正式进入中国市场前便已扎根——1996年，我们在苏州投建工厂，如今已发展为集团全球最大产能制造基地，也是欧莱雅全球制造体系的标杆项目。",
    "PDF链接": "https://paper.people.com.cn/rmrbhwb/pc/attachement/202607/04/013e1b17-3a77-40ab-bbad-26d8f1808a15.pdf",
    "文章链接": "https://paper.people.com.cn/rmrbhwb/pc/content/202607/04/content_30166634.html",
    "匹配行业": "美妆",
    "匹配关键词": "欧莱雅"
  }
]